zycelium/dataconfig/__init__.py
zycelium.dataconfig-0.1.1.dist-info/LICENSE
zycelium.dataconfig-0.1.1.dist-info/METADATA
zycelium.dataconfig-0.1.1.dist-info/WHEEL
zycelium.dataconfig-0.1.1.dist-info/top_level.txt
zycelium.dataconfig-0.1.1.dist-info/RECORD
