Metadata-Version: 2.1
Name: zycelium.dataconfig
Version: 0.1.1
Summary: Create dataclasses backed by configuration files.
Home-page: https://github.com/zycelium/python-dataconfig
Author: Harshad Sharma
Author-email: harshad@sharma.io
License: UNKNOWN
Project-URL: Bug Tracker, https://github.com/zycelium/python-dataconfig/issues
Platform: UNKNOWN
Classifier: Programming Language :: Python :: 3
Classifier: License :: OSI Approved :: BSD License
Classifier: Operating System :: OS Independent
Classifier: Development Status :: 3 - Alpha
Requires-Python: >=3.7
License-File: LICENSE
Requires-Dist: click (>=8.0)
Requires-Dist: configobj (>=5.0)
Provides-Extra: devel
Requires-Dist: bump2version (>=1.0) ; extra == 'devel'
Requires-Dist: pytest (>=6.2) ; extra == 'devel'
